LICENSE
MANIFEST.in
README.rst
setup.cfg
setup.py
docs/authors.rst
docs/autodoc.rst
docs/conf.py
docs/contributing.rst
docs/index.rst
docs/installation.rst
docs/kerasltiprovider.rst
docs/modules.rst
docs/readme.rst
docs/usage.rst
kerasltiprovider/__init__.py
kerasltiprovider/assignment.py
kerasltiprovider/cli.py
kerasltiprovider/config.py
kerasltiprovider/context.py
kerasltiprovider/database.py
kerasltiprovider/exceptions.py
kerasltiprovider/ingest.py
kerasltiprovider/interceptors.py
kerasltiprovider/processing.py
kerasltiprovider/provider.py
kerasltiprovider/selection.py
kerasltiprovider/server.py
kerasltiprovider/submission.py
kerasltiprovider/tracer.py
kerasltiprovider/types.py
kerasltiprovider/utils.py
kerasltiprovider/validation.py
kerasltiprovider.egg-info/PKG-INFO
kerasltiprovider.egg-info/SOURCES.txt
kerasltiprovider.egg-info/dependency_links.txt
kerasltiprovider.egg-info/entry_points.txt
kerasltiprovider.egg-info/not-zip-safe
kerasltiprovider.egg-info/requires.txt
kerasltiprovider.egg-info/top_level.txt
tests/common.py
tests/test_hashing.py
tests/test_kerasltiprovider.py
tests/test_submission_validation.py